{
	"cmake" : 
	{
		"generator" : 
		{
			"multiConfig" : false,
			"name" : "Ninja"
		},
		"paths" : 
		{
			"cmake" : "/usr/bin/cmake",
			"cpack" : "/usr/bin/cpack",
			"ctest" : "/usr/bin/ctest",
			"root" : "/usr/share/cmake"
		},
		"version" : 
		{
			"isDirty" : false,
			"major" : 3,
			"minor" : 26,
			"patch" : 3,
			"string" : "3.26.3",
			"suffix" : ""
		}
	},
	"objects" : 
	[
		{
			"jsonFile" : "codemodel-v2-50813e040ba233498d53.json",
			"kind" : "codemodel",
			"version" : 
			{
				"major" : 2,
				"minor" : 5
			}
		},
		{
			"jsonFile" : "cache-v2-13bd13e69737ed692990.json",
			"kind" : "cache",
			"version" : 
			{
				"major" : 2,
				"minor" : 0
			}
		},
		{
			"jsonFile" : "cmakeFiles-v1-e01ed0bbd59d7f774169.json",
			"kind" : "cmakeFiles",
			"version" : 
			{
				"major" : 1,
				"minor" : 0
			}
		},
		{
			"jsonFile" : "toolchains-v1-26ba4dac0beda2ae070b.json",
			"kind" : "toolchains",
			"version" : 
			{
				"major" : 1,
				"minor" : 0
			}
		}
	],
	"reply" : 
	{
		"client-integration-vscode" : 
		{
			"cache-v2" : 
			{
				"jsonFile" : "cache-v2-13bd13e69737ed692990.json",
				"kind" : "cache",
				"version" : 
				{
					"major" : 2,
					"minor" : 0
				}
			},
			"cmakeFiles-v1" : 
			{
				"jsonFile" : "cmakeFiles-v1-e01ed0bbd59d7f774169.json",
				"kind" : "cmakeFiles",
				"version" : 
				{
					"major" : 1,
					"minor" : 0
				}
			},
			"codemodel-v2" : 
			{
				"jsonFile" : "codemodel-v2-50813e040ba233498d53.json",
				"kind" : "codemodel",
				"version" : 
				{
					"major" : 2,
					"minor" : 5
				}
			}
		},
		"client-vscode" : 
		{
			"query.json" : 
			{
				"requests" : 
				[
					{
						"kind" : "cache",
						"version" : 2
					},
					{
						"kind" : "codemodel",
						"version" : 2
					},
					{
						"kind" : "toolchains",
						"version" : 1
					},
					{
						"kind" : "cmakeFiles",
						"version" : 1
					}
				],
				"responses" : 
				[
					{
						"jsonFile" : "cache-v2-13bd13e69737ed692990.json",
						"kind" : "cache",
						"version" : 
						{
							"major" : 2,
							"minor" : 0
						}
					},
					{
						"jsonFile" : "codemodel-v2-50813e040ba233498d53.json",
						"kind" : "codemodel",
						"version" : 
						{
							"major" : 2,
							"minor" : 5
						}
					},
					{
						"jsonFile" : "toolchains-v1-26ba4dac0beda2ae070b.json",
						"kind" : "toolchains",
						"version" : 
						{
							"major" : 1,
							"minor" : 0
						}
					},
					{
						"jsonFile" : "cmakeFiles-v1-e01ed0bbd59d7f774169.json",
						"kind" : "cmakeFiles",
						"version" : 
						{
							"major" : 1,
							"minor" : 0
						}
					}
				]
			}
		}
	}
}
